LICENSE
MANIFEST.in
README.md
requirements.txt
setup.py
pdf2docxnogui/__init__.py
pdf2docxnogui/converter.py
pdf2docxnogui/main.py
pdf2docxnogui.egg-info/PKG-INFO
pdf2docxnogui.egg-info/SOURCES.txt
pdf2docxnogui.egg-info/dependency_links.txt
pdf2docxnogui.egg-info/entry_points.txt
pdf2docxnogui.egg-info/not-zip-safe
pdf2docxnogui.egg-info/requires.txt
pdf2docxnogui.egg-info/top_level.txt
pdf2docxnogui/common/Block.py
pdf2docxnogui/common/Collection.py
pdf2docxnogui/common/Element.py
pdf2docxnogui/common/__init__.py
pdf2docxnogui/common/constants.py
pdf2docxnogui/common/docx.py
pdf2docxnogui/common/share.py
pdf2docxnogui/font/Fonts.py
pdf2docxnogui/font/__init__.py
pdf2docxnogui/image/Image.py
pdf2docxnogui/image/ImageBlock.py
pdf2docxnogui/image/ImageSpan.py
pdf2docxnogui/image/ImagesExtractor.py
pdf2docxnogui/image/__init__.py
pdf2docxnogui/layout/Blocks.py
pdf2docxnogui/layout/Column.py
pdf2docxnogui/layout/Layout.py
pdf2docxnogui/layout/Section.py
pdf2docxnogui/layout/Sections.py
pdf2docxnogui/layout/__init__.py
pdf2docxnogui/page/BasePage.py
pdf2docxnogui/page/Page.py
pdf2docxnogui/page/Pages.py
pdf2docxnogui/page/RawPage.py
pdf2docxnogui/page/__init__.py
pdf2docxnogui/shape/Path.py
pdf2docxnogui/shape/Paths.py
pdf2docxnogui/shape/Shape.py
pdf2docxnogui/shape/Shapes.py
pdf2docxnogui/shape/__init__.py
pdf2docxnogui/table/Border.py
pdf2docxnogui/table/Cell.py
pdf2docxnogui/table/Cells.py
pdf2docxnogui/table/Row.py
pdf2docxnogui/table/Rows.py
pdf2docxnogui/table/TableBlock.py
pdf2docxnogui/table/TableStructure.py
pdf2docxnogui/table/TablesConstructor.py
pdf2docxnogui/table/__init__.py
pdf2docxnogui/text/Char.py
pdf2docxnogui/text/Line.py
pdf2docxnogui/text/Lines.py
pdf2docxnogui/text/Spans.py
pdf2docxnogui/text/TextBlock.py
pdf2docxnogui/text/TextSpan.py
pdf2docxnogui/text/__init__.py
test/local_test.py
test/test.py
test/samples/demo-blank.pdf
test/samples/demo-image-cmyk.pdf
test/samples/demo-image-transparent.pdf
test/samples/demo-image-vector-graphic.pdf
test/samples/demo-image.pdf
test/samples/demo-path-transformation.pdf
test/samples/demo-section-spacing.pdf
test/samples/demo-section.pdf
test/samples/demo-table-align-borders.pdf
test/samples/demo-table-border-style.pdf
test/samples/demo-table-bottom.pdf
