Metadata-Version: 2.1
Name: pdf2docxnogui
Version: 0.1
Summary: parse PDF files to docx
Home-page: https://github.com/dothinking/pdf2docxnogui
Author: dothinking
Author-email: train8808@gmail.com
License: GPL v3
Keywords: pdf-to-word,pdf-to-docx
Platform: UNKNOWN
Requires-Python: >=3.6
